flask_chown/__init__.py
flask_chown/permission_manager.py
flask_chown/permission_manager_redis.py
flask_chown-0.2.1.dist-info/LICENSE.txt
flask_chown-0.2.1.dist-info/METADATA
flask_chown-0.2.1.dist-info/RECORD
flask_chown-0.2.1.dist-info/WHEEL
flask_chown-0.2.1.dist-info/top_level.txt
