Metadata-Version: 2.1
Name: flask-chown
Version: 0.2.1
Summary: Flask permissions the UNIX way using owner and groups
Home-page: https://github.com/xvzf/flask-chown
Author: Matthias Riegler
Author-email: matthias@xvzf.tech
License: UNKNOWN
Project-URL: Bug Reports, https://github.com/xvzf/flask-chown/issues
Project-URL: Source, https://github.com/xvzf/flask-chown/
Keywords: flask permission flask-login flask-principal
Platform: UNKNOWN
Classifier: Development Status :: 5 - Production/Stable
Classifier: Intended Audience :: Developers
Classifier: License :: OSI Approved :: Apache Software License
Classifier: Framework :: Flask
Classifier: Programming Language :: Python
Classifier: Programming Language :: Python :: 3
Provides-Extra: caching support
Requires-Dist: flask
Provides-Extra: caching support
Requires-Dist: redis; extra == 'caching support'
